wagtail_contact_reply/__init__.py
wagtail_contact_reply/admin.py
wagtail_contact_reply/apps.py
wagtail_contact_reply/forms.py
wagtail_contact_reply/migrations/__init__.py
wagtail_contact_reply/models.py
wagtail_contact_reply/templates/wagtailforms/list_submissions.html
wagtail_contact_reply/templates/wagtailforms/reply.html
wagtail_contact_reply/views.py
wagtail_contact_reply/wagtail_hooks.py
wagtail_contact_reply-0.1.0.dist-info/LICENSE
wagtail_contact_reply-0.1.0.dist-info/WHEEL
wagtail_contact_reply-0.1.0.dist-info/METADATA
wagtail_contact_reply-0.1.0.dist-info/RECORD
