Metadata-Version: 2.1
Name: wagtail-contact-reply
Version: 0.1.0
Summary: Reply to contact form submissions directly from Wagtail
Home-page: https://github.com/KalobTaulien/wagtail-contact-reply
Author: Kalob Taulien
Author-email: kalob.taulien@gmail.com
Requires-Python: >=3.6,<=3.8
Classifier: Environment :: Web Environment
Classifier: Framework :: Django
Classifier: Framework :: Django :: 2.2
Classifier: Framework :: Wagtail
Classifier: Framework :: Wagtail :: 2
Classifier: Intended Audience :: Developers
Classifier: License :: OSI Approved :: BSD License
Classifier: Operating System :: OS Independent
Classifier: Programming Language :: Python
Classifier: Programming Language :: Python :: 3
Classifier: Programming Language :: Python :: 3.6
Classifier: Programming Language :: Python :: 3.7
Classifier: Programming Language :: Python :: 3.8
Classifier: Topic :: Internet :: WWW/HTTP
Classifier: Topic :: Internet :: WWW/HTTP :: Dynamic Content
Requires-Dist: wagtail (>=2.6)
Project-URL: Repository, https://github.com/KalobTaulien/wagtail-contact-reply
